LICENSE
pyproject.toml
readme.md
setup.py
batchgeneratorsv2/__init__.py
batchgeneratorsv2.egg-info/PKG-INFO
batchgeneratorsv2.egg-info/SOURCES.txt
batchgeneratorsv2.egg-info/dependency_links.txt
batchgeneratorsv2.egg-info/requires.txt
batchgeneratorsv2.egg-info/top_level.txt
batchgeneratorsv2/benchmarks/__init__.py
batchgeneratorsv2/benchmarks/unique_values.py
batchgeneratorsv2/benchmarks/bg_comparison/__init__.py
batchgeneratorsv2/benchmarks/bg_comparison/nnUNet_pipeline_bg.py
batchgeneratorsv2/benchmarks/bg_comparison/nnUNet_pipeline_here.py
batchgeneratorsv2/dataloading/__init__.py
batchgeneratorsv2/helpers/__init__.py
batchgeneratorsv2/helpers/scalar_type.py
batchgeneratorsv2/transforms/__init__.py
batchgeneratorsv2/transforms/base/__init__.py
batchgeneratorsv2/transforms/base/basic_transform.py
batchgeneratorsv2/transforms/intensity/__init__.py
batchgeneratorsv2/transforms/intensity/brightness.py
batchgeneratorsv2/transforms/intensity/contrast.py
batchgeneratorsv2/transforms/intensity/gamma.py
batchgeneratorsv2/transforms/intensity/gaussian_noise.py
batchgeneratorsv2/transforms/nnunet/__init__.py
batchgeneratorsv2/transforms/nnunet/random_binary_operator.py
batchgeneratorsv2/transforms/nnunet/remove_connected_components.py
batchgeneratorsv2/transforms/nnunet/seg_to_onehot.py
batchgeneratorsv2/transforms/noise/__init__.py
batchgeneratorsv2/transforms/noise/gaussian_blur.py
batchgeneratorsv2/transforms/spatial/__init__.py
batchgeneratorsv2/transforms/spatial/low_resolution.py
batchgeneratorsv2/transforms/spatial/mirroring.py
batchgeneratorsv2/transforms/spatial/spatial.py
batchgeneratorsv2/transforms/utils/__init__.py
batchgeneratorsv2/transforms/utils/compose.py
batchgeneratorsv2/transforms/utils/cropping.py
batchgeneratorsv2/transforms/utils/deep_supervision_downsampling.py
batchgeneratorsv2/transforms/utils/nnunet_masking.py
batchgeneratorsv2/transforms/utils/pseudo2d.py
batchgeneratorsv2/transforms/utils/random.py
batchgeneratorsv2/transforms/utils/remove_label.py
batchgeneratorsv2/transforms/utils/seg_to_regions.py