Metadata-Version: 2.1
Name: batchgeneratorsv2
Version: 0.2
Summary: Batchgenerators but better
Author: Helmholtz Imaging Applied Computer Vision Lab
Author-email: Fabian Isensee <f.isensee@dkfz-heidelberg.de>
License:                                  Apache License
Keywords: deep learning,image segmentation,semantic segmentation,medical image analysis,medical image segmentation,nnU-Net,nnunet
Classifier: Development Status :: 1 - Planning
Classifier: Intended Audience :: Developers
Classifier: Intended Audience :: Science/Research
Classifier: Intended Audience :: Healthcare Industry
Classifier: Programming Language :: Python :: 3
Classifier: License :: OSI Approved :: Apache Software License
Classifier: Topic :: Scientific/Engineering :: Artificial Intelligence
Classifier: Topic :: Scientific/Engineering :: Image Recognition
Classifier: Topic :: Scientific/Engineering :: Medical Science Apps.
Requires-Python: >=3.9
License-File: LICENSE
Requires-Dist: torch>=2.0.0
Requires-Dist: numpy
Requires-Dist: fft-conv-pytorch
Requires-Dist: batchgenerators>=0.25
